{"title": "聊不来v2", "id": "tg-949045291170922497", "net.maunium.telegram.pack": {"short_name": "liaobulaiv2", "hash": "-532718963"}, "stickers": [{"body": "😂", "url": "mxc://m.origincode.me/VdgU5TNbe9lj1wiEJL6cLte4WlZMLENu", "info": {"w": 256, "h": 226, "size": 77819, "mimetype": "image/png", "thumbnail_url": "mxc://m.origincode.me/VdgU5TNbe9lj1wiEJL6cLte4WlZMLENu", "thumbnail_info": {"w": 256, "h": 226, "size": 77819, "mimetype": "image/png"}}, "msgtype": "m.sticker", "id": "tg-949045291170922510", "net.maunium.telegram.sticker": {"pack": {"id": "949045291170922497", "short_name": "liaobulaiv2"}, "id": "949045291170922510", "emoticons": ["😂"]}}, {"body": "😂", "url": "mxc://m.origincode.me/N1I3SOoZPQ6te6ioTHBDXyjFD6MyehF9", "info": {"w": 256, "h": 226, "size": 83945, "mimetype": "image/png", "thumbnail_url": "mxc://m.origincode.me/N1I3SOoZPQ6te6ioTHBDXyjFD6MyehF9", "thumbnail_info": {"w": 256, "h": 226, "size": 83945, "mimetype": "image/png"}}, "msgtype": "m.sticker", "id": "tg-949045291170922511", "net.maunium.telegram.sticker": {"pack": {"id": "949045291170922497", "short_name": "liaobulaiv2"}, "id": "949045291170922511", "emoticons": ["😂"]}}, {"body": "😂", "url": "mxc://m.origincode.me/HT3gVZT2h8JNgpnnVYIkqPHywhU59hqU", "info": {"w": 256, "h": 226, "size": 102268, "mimetype": "image/png", "thumbnail_url": "mxc://m.origincode.me/HT3gVZT2h8JNgpnnVYIkqPHywhU59hqU", "thumbnail_info": {"w": 256, "h": 226, "size": 102268, "mimetype": "image/png"}}, "msgtype": "m.sticker", "id": "tg-949045291170922512", "net.maunium.telegram.sticker": {"pack": {"id": "949045291170922497", "short_name": "liaobulaiv2"}, "id": "949045291170922512", "emoticons": ["😂"]}}, {"body": "😂", "url": "mxc://m.origincode.me/uhTMsmihsnGildNr52wj8SMlADI93x2g", "info": {"w": 256, "h": 226, "size": 82719, "mimetype": "image/png", "thumbnail_url": "mxc://m.origincode.me/uhTMsmihsnGildNr52wj8SMlADI93x2g", "thumbnail_info": {"w": 256, "h": 226, "size": 82719, "mimetype": "image/png"}}, "msgtype": "m.sticker", "id": "tg-949045291170922513", "net.maunium.telegram.sticker": {"pack": {"id": "949045291170922497", "short_name": "liaobulaiv2"}, "id": "949045291170922513", "emoticons": ["😂"]}}, {"body": "👍", "url": "mxc://m.origincode.me/qSUsfIZEnwUDljexh2pJhsHVFc51xdhn", "info": {"w": 256, "h": 226, "size": 109729, "mimetype": "image/png", "thumbnail_url": "mxc://m.origincode.me/qSUsfIZEnwUDljexh2pJhsHVFc51xdhn", "thumbnail_info": {"w": 256, "h": 226, "size": 109729, "mimetype": "image/png"}}, "msgtype": "m.sticker", "id": "tg-949045291170922514", "net.maunium.telegram.sticker": {"pack": {"id": "949045291170922497", "short_name": "liaobulaiv2"}, "id": "949045291170922514", "emoticons": ["👍"]}}]}