{"title": "Linux distributions", "id": "tg-114159788346048513", "net.maunium.telegram.pack": {"short_name": "linuxdistro", "hash": "1021907490"}, "stickers": [{"body": "😘", "url": "mxc://m.origincode.me/D3b6bDRA0ikOlcDOVK3CozDhUa74uusH", "info": {"w": 256, "h": 256, "size": 93192, "mimetype": "image/png", "thumbnail_url": "mxc://m.origincode.me/D3b6bDRA0ikOlcDOVK3CozDhUa74uusH", "thumbnail_info": {"w": 256, "h": 256, "size": 93192, "mimetype": "image/png"}}, "msgtype": "m.sticker", "id": "tg-114159788346048700", "net.maunium.telegram.sticker": {"pack": {"id": "114159788346048513", "short_name": "linuxdistro"}, "id": "114159788346048700", "emoticons": ["😘"]}}, {"body": "👇", "url": "mxc://m.origincode.me/VDId0UukhsIEzituFm0KtXIicep2QHZE", "info": {"w": 256, "h": 256, "size": 213642, "mimetype": "image/png", "thumbnail_url": "mxc://m.origincode.me/VDId0UukhsIEzituFm0KtXIicep2QHZE", "thumbnail_info": {"w": 256, "h": 256, "size": 213642, "mimetype": "image/png"}}, "msgtype": "m.sticker", "id": "tg-114159788346048843", "net.maunium.telegram.sticker": {"pack": {"id": "114159788346048513", "short_name": "linuxdistro"}, "id": "114159788346048843", "emoticons": ["👇"]}}, {"body": "👍", "url": "mxc://m.origincode.me/dNpZ6L866TM1jiwydkrSRKk5QDrN1U2t", "info": {"w": 256, "h": 256, "size": 65173, "mimetype": "image/png", "thumbnail_url": "mxc://m.origincode.me/dNpZ6L866TM1jiwydkrSRKk5QDrN1U2t", "thumbnail_info": {"w": 256, "h": 256, "size": 65173, "mimetype": "image/png"}}, "msgtype": "m.sticker", "id": "tg-114159788346048706", "net.maunium.telegram.sticker": {"pack": {"id": "114159788346048513", "short_name": "linuxdistro"}, "id": "114159788346048706", "emoticons": ["👍"]}}, {"body": "👍", "url": "mxc://m.origincode.me/T0AYzSUync0nc5tjSSqBqihMpsWOey0j", "info": {"w": 256, "h": 256, "size": 88780, "mimetype": "image/png", "thumbnail_url": "mxc://m.origincode.me/T0AYzSUync0nc5tjSSqBqihMpsWOey0j", "thumbnail_info": {"w": 256, "h": 256, "size": 88780, "mimetype": "image/png"}}, "msgtype": "m.sticker", "id": "tg-114159788346048691", "net.maunium.telegram.sticker": {"pack": {"id": "114159788346048513", "short_name": "linuxdistro"}, "id": "114159788346048691", "emoticons": ["👍"]}}, {"body": "💻", "url": "mxc://m.origincode.me/u6AHFEya8rcCyzq20FAqR6KJmJz2jNtr", "info": {"w": 256, "h": 256, "size": 65381, "mimetype": "image/png", "thumbnail_url": "mxc://m.origincode.me/u6AHFEya8rcCyzq20FAqR6KJmJz2jNtr", "thumbnail_info": {"w": 256, "h": 256, "size": 65381, "mimetype": "image/png"}}, "msgtype": "m.sticker", "id": "tg-114159788346049066", "net.maunium.telegram.sticker": {"pack": {"id": "114159788346048513", "short_name": "linuxdistro"}, "id": "114159788346049066", "emoticons": ["💻"]}}, {"body": "😄", "url": "mxc://m.origincode.me/xo1CUwO7yydmzlJo2oURlotYl4cPuSw5", "info": {"w": 256, "h": 256, "size": 134055, "mimetype": "image/png", "thumbnail_url": "mxc://m.origincode.me/xo1CUwO7yydmzlJo2oURlotYl4cPuSw5", "thumbnail_info": {"w": 256, "h": 256, "size": 134055, "mimetype": "image/png"}}, "msgtype": "m.sticker", "id": "tg-114159788346048689", "net.maunium.telegram.sticker": {"pack": {"id": "114159788346048513", "short_name": "linuxdistro"}, "id": "114159788346048689", "emoticons": ["😄"]}}, {"body": "😀", "url": "mxc://m.origincode.me/ZNCsoCus4IXvvXz61sYmfZ8u2AWjb9IV", "info": {"w": 256, "h": 256, "size": 78073, "mimetype": "image/png", "thumbnail_url": "mxc://m.origincode.me/ZNCsoCus4IXvvXz61sYmfZ8u2AWjb9IV", "thumbnail_info": {"w": 256, "h": 256, "size": 78073, "mimetype": "image/png"}}, "msgtype": "m.sticker", "id": "tg-114159788346048693", "net.maunium.telegram.sticker": {"pack": {"id": "114159788346048513", "short_name": "linuxdistro"}, "id": "114159788346048693", "emoticons": ["😀"]}}, {"body": "😀", "url": "mxc://m.origincode.me/4JCWMH7wGKjKweUbIZWZ5ocw32w6WxWK", "info": {"w": 256, "h": 256, "size": 112841, "mimetype": "image/png", "thumbnail_url": "mxc://m.origincode.me/4JCWMH7wGKjKweUbIZWZ5ocw32w6WxWK", "thumbnail_info": {"w": 256, "h": 256, "size": 112841, "mimetype": "image/png"}}, "msgtype": "m.sticker", "id": "tg-114159788346048695", "net.maunium.telegram.sticker": {"pack": {"id": "114159788346048513", "short_name": "linuxdistro"}, "id": "114159788346048695", "emoticons": ["😀"]}}, {"body": "😄", "url": "mxc://m.origincode.me/eDsa1jnBn4VryQaEdou79pAy3ODMamGa", "info": {"w": 256, "h": 256, "size": 245901, "mimetype": "image/png", "thumbnail_url": "mxc://m.origincode.me/eDsa1jnBn4VryQaEdou79pAy3ODMamGa", "thumbnail_info": {"w": 256, "h": 256, "size": 245901, "mimetype": "image/png"}}, "msgtype": "m.sticker", "id": "tg-114159788346048698", "net.maunium.telegram.sticker": {"pack": {"id": "114159788346048513", "short_name": "linuxdistro"}, "id": "114159788346048698", "emoticons": ["😄"]}}, {"body": "🐑", "url": "mxc://m.origincode.me/VI49kL5O5OTWkzm5NaVaPoKgkil4L0qb", "info": {"w": 256, "h": 256, "size": 117665, "mimetype": "image/png", "thumbnail_url": "mxc://m.origincode.me/VI49kL5O5OTWkzm5NaVaPoKgkil4L0qb", "thumbnail_info": {"w": 256, "h": 256, "size": 117665, "mimetype": "image/png"}}, "msgtype": "m.sticker", "id": "tg-114159788346048702", "net.maunium.telegram.sticker": {"pack": {"id": "114159788346048513", "short_name": "linuxdistro"}, "id": "114159788346048702", "emoticons": ["🐑"]}}, {"body": "😎", "url": "mxc://m.origincode.me/rkLfoIV6h8DIU6C5HtD2dsB1DR7CcRPw", "info": {"w": 256, "h": 256, "size": 188169, "mimetype": "image/png", "thumbnail_url": "mxc://m.origincode.me/rkLfoIV6h8DIU6C5HtD2dsB1DR7CcRPw", "thumbnail_info": {"w": 256, "h": 256, "size": 188169, "mimetype": "image/png"}}, "msgtype": "m.sticker", "id": "tg-114159788346048709", "net.maunium.telegram.sticker": {"pack": {"id": "114159788346048513", "short_name": "linuxdistro"}, "id": "114159788346048709", "emoticons": ["😎"]}}, {"body": "🐊", "url": "mxc://m.origincode.me/d1ZmX6dy0wFomt7AV2C39UyIyIoXmb00", "info": {"w": 256, "h": 256, "size": 88410, "mimetype": "image/png", "thumbnail_url": "mxc://m.origincode.me/d1ZmX6dy0wFomt7AV2C39UyIyIoXmb00", "thumbnail_info": {"w": 256, "h": 256, "size": 88410, "mimetype": "image/png"}}, "msgtype": "m.sticker", "id": "tg-114159788346048711", "net.maunium.telegram.sticker": {"pack": {"id": "114159788346048513", "short_name": "linuxdistro"}, "id": "114159788346048711", "emoticons": ["🐊"]}}, {"body": "😳", "url": "mxc://m.origincode.me/1TDAUDqMgEmYw1wvUJtN1lU1yl1wRak8", "info": {"w": 256, "h": 256, "size": 93815, "mimetype": "image/png", "thumbnail_url": "mxc://m.origincode.me/1TDAUDqMgEmYw1wvUJtN1lU1yl1wRak8", "thumbnail_info": {"w": 256, "h": 256, "size": 93815, "mimetype": "image/png"}}, "msgtype": "m.sticker", "id": "tg-114159788346048716", "net.maunium.telegram.sticker": {"pack": {"id": "114159788346048513", "short_name": "linuxdistro"}, "id": "114159788346048716", "emoticons": ["😳"]}}, {"body": "⭐", "url": "mxc://m.origincode.me/F8ZSm7yPvXRJ3ughRICTsmVi2DnBtNm3", "info": {"w": 256, "h": 256, "size": 163469, "mimetype": "image/png", "thumbnail_url": "mxc://m.origincode.me/F8ZSm7yPvXRJ3ughRICTsmVi2DnBtNm3", "thumbnail_info": {"w": 256, "h": 256, "size": 163469, "mimetype": "image/png"}}, "msgtype": "m.sticker", "id": "tg-114159788346048718", "net.maunium.telegram.sticker": {"pack": {"id": "114159788346048513", "short_name": "linuxdistro"}, "id": "114159788346048718", "emoticons": ["⭐"]}}, {"body": "😌", "url": "mxc://m.origincode.me/0RGxxgoIbd0rNfH4cUNsaef2BezVK0Em", "info": {"w": 256, "h": 256, "size": 221812, "mimetype": "image/png", "thumbnail_url": "mxc://m.origincode.me/0RGxxgoIbd0rNfH4cUNsaef2BezVK0Em", "thumbnail_info": {"w": 256, "h": 256, "size": 221812, "mimetype": "image/png"}}, "msgtype": "m.sticker", "id": "tg-114159788346048720", "net.maunium.telegram.sticker": {"pack": {"id": "114159788346048513", "short_name": "linuxdistro"}, "id": "114159788346048720", "emoticons": ["😌"]}}, {"body": "⭐", "url": "mxc://m.origincode.me/blHAKnzbi3UwQAbGsQjZxsidHdRR5UvX", "info": {"w": 256, "h": 256, "size": 101504, "mimetype": "image/png", "thumbnail_url": "mxc://m.origincode.me/blHAKnzbi3UwQAbGsQjZxsidHdRR5UvX", "thumbnail_info": {"w": 256, "h": 256, "size": 101504, "mimetype": "image/png"}}, "msgtype": "m.sticker", "id": "tg-114159788346048724", "net.maunium.telegram.sticker": {"pack": {"id": "114159788346048513", "short_name": "linuxdistro"}, "id": "114159788346048724", "emoticons": ["⭐"]}}, {"body": "🎥", "url": "mxc://m.origincode.me/z9JHpbvN5054bH9jQEupB3FXKFkoxO5t", "info": {"w": 256, "h": 256, "size": 36785, "mimetype": "image/png", "thumbnail_url": "mxc://m.origincode.me/z9JHpbvN5054bH9jQEupB3FXKFkoxO5t", "thumbnail_info": {"w": 256, "h": 256, "size": 36785, "mimetype": "image/png"}}, "msgtype": "m.sticker", "id": "tg-114159788346048726", "net.maunium.telegram.sticker": {"pack": {"id": "114159788346048513", "short_name": "linuxdistro"}, "id": "114159788346048726", "emoticons": ["🎥"]}}, {"body": "💻", "url": "mxc://m.origincode.me/PRUYuLiK3RA0SScmQmT950vDEhSDAq50", "info": {"w": 256, "h": 256, "size": 118281, "mimetype": "image/png", "thumbnail_url": "mxc://m.origincode.me/PRUYuLiK3RA0SScmQmT950vDEhSDAq50", "thumbnail_info": {"w": 256, "h": 256, "size": 118281, "mimetype": "image/png"}}, "msgtype": "m.sticker", "id": "tg-114159788346048728", "net.maunium.telegram.sticker": {"pack": {"id": "114159788346048513", "short_name": "linuxdistro"}, "id": "114159788346048728", "emoticons": ["💻"]}}, {"body": "🎁", "url": "mxc://m.origincode.me/4BHvXfV3hXa9kwefLzCoHw4lst9pro3g", "info": {"w": 256, "h": 256, "size": 7823, "mimetype": "image/png", "thumbnail_url": "mxc://m.origincode.me/4BHvXfV3hXa9kwefLzCoHw4lst9pro3g", "thumbnail_info": {"w": 256, "h": 256, "size": 7823, "mimetype": "image/png"}}, "msgtype": "m.sticker", "id": "tg-114159788346048730", "net.maunium.telegram.sticker": {"pack": {"id": "114159788346048513", "short_name": "linuxdistro"}, "id": "114159788346048730", "emoticons": ["🎁"]}}, {"body": "😌", "url": "mxc://m.origincode.me/A1tMI9KKT8S6QB545J8DG2QtaVpAfCcx", "info": {"w": 256, "h": 256, "size": 26361, "mimetype": "image/png", "thumbnail_url": "mxc://m.origincode.me/A1tMI9KKT8S6QB545J8DG2QtaVpAfCcx", "thumbnail_info": {"w": 256, "h": 256, "size": 26361, "mimetype": "image/png"}}, "msgtype": "m.sticker", "id": "tg-114159788346048732", "net.maunium.telegram.sticker": {"pack": {"id": "114159788346048513", "short_name": "linuxdistro"}, "id": "114159788346048732", "emoticons": ["😌"]}}, {"body": "🐶", "url": "mxc://m.origincode.me/80Jm3HbRXhcrsh4UNIUuXVXY75MHmqiE", "info": {"w": 256, "h": 256, "size": 131856, "mimetype": "image/png", "thumbnail_url": "mxc://m.origincode.me/80Jm3HbRXhcrsh4UNIUuXVXY75MHmqiE", "thumbnail_info": {"w": 256, "h": 256, "size": 131856, "mimetype": "image/png"}}, "msgtype": "m.sticker", "id": "tg-114159788346048734", "net.maunium.telegram.sticker": {"pack": {"id": "114159788346048513", "short_name": "linuxdistro"}, "id": "114159788346048734", "emoticons": ["🐶"]}}, {"body": "😳", "url": "mxc://m.origincode.me/8aurwFMOH1BCKYQpa0dkDZVHKMXiDH1q", "info": {"w": 256, "h": 256, "size": 159596, "mimetype": "image/png", "thumbnail_url": "mxc://m.origincode.me/8aurwFMOH1BCKYQpa0dkDZVHKMXiDH1q", "thumbnail_info": {"w": 256, "h": 256, "size": 159596, "mimetype": "image/png"}}, "msgtype": "m.sticker", "id": "tg-114159788346049060", "net.maunium.telegram.sticker": {"pack": {"id": "114159788346048513", "short_name": "linuxdistro"}, "id": "114159788346049060", "emoticons": ["😳"]}}, {"body": "🍃", "url": "mxc://m.origincode.me/sONtjiKQuiMBg1R3kwHA9UoDM4MUJPU5", "info": {"w": 256, "h": 256, "size": 207356, "mimetype": "image/png", "thumbnail_url": "mxc://m.origincode.me/sONtjiKQuiMBg1R3kwHA9UoDM4MUJPU5", "thumbnail_info": {"w": 256, "h": 256, "size": 207356, "mimetype": "image/png"}}, "msgtype": "m.sticker", "id": "tg-114159788346048736", "net.maunium.telegram.sticker": {"pack": {"id": "114159788346048513", "short_name": "linuxdistro"}, "id": "114159788346048736", "emoticons": ["🍃"]}}, {"body": "🐧", "url": "mxc://m.origincode.me/DbWXRzFVePxgpZLmwrAOJcFJZFtKhOVC", "info": {"w": 256, "h": 256, "size": 125782, "mimetype": "image/png", "thumbnail_url": "mxc://m.origincode.me/DbWXRzFVePxgpZLmwrAOJcFJZFtKhOVC", "thumbnail_info": {"w": 256, "h": 256, "size": 125782, "mimetype": "image/png"}}, "msgtype": "m.sticker", "id": "tg-114159788346048738", "net.maunium.telegram.sticker": {"pack": {"id": "114159788346048513", "short_name": "linuxdistro"}, "id": "114159788346048738", "emoticons": ["🐧"]}}, {"body": "😐", "url": "mxc://m.origincode.me/k0a10C3l2hsyINQgJooptkjNU3WLTVif", "info": {"w": 256, "h": 256, "size": 128702, "mimetype": "image/png", "thumbnail_url": "mxc://m.origincode.me/k0a10C3l2hsyINQgJooptkjNU3WLTVif", "thumbnail_info": {"w": 256, "h": 256, "size": 128702, "mimetype": "image/png"}}, "msgtype": "m.sticker", "id": "tg-114159788346048746", "net.maunium.telegram.sticker": {"pack": {"id": "114159788346048513", "short_name": "linuxdistro"}, "id": "114159788346048746", "emoticons": ["😐"]}}, {"body": "😊", "url": "mxc://m.origincode.me/VCUWCTZCt0QBEbN9XIygeqRGCm0TBlVF", "info": {"w": 256, "h": 256, "size": 144919, "mimetype": "image/png", "thumbnail_url": "mxc://m.origincode.me/VCUWCTZCt0QBEbN9XIygeqRGCm0TBlVF", "thumbnail_info": {"w": 256, "h": 256, "size": 144919, "mimetype": "image/png"}}, "msgtype": "m.sticker", "id": "tg-114159788346048748", "net.maunium.telegram.sticker": {"pack": {"id": "114159788346048513", "short_name": "linuxdistro"}, "id": "114159788346048748", "emoticons": ["😊"]}}, {"body": "😃", "url": "mxc://m.origincode.me/xShukHK3IyKJZmXymdlwKUjbSSek73DL", "info": {"w": 256, "h": 256, "size": 82456, "mimetype": "image/png", "thumbnail_url": "mxc://m.origincode.me/xShukHK3IyKJZmXymdlwKUjbSSek73DL", "thumbnail_info": {"w": 256, "h": 256, "size": 82456, "mimetype": "image/png"}}, "msgtype": "m.sticker", "id": "tg-114159788346048750", "net.maunium.telegram.sticker": {"pack": {"id": "114159788346048513", "short_name": "linuxdistro"}, "id": "114159788346048750", "emoticons": ["😃"]}}, {"body": "🐭", "url": "mxc://m.origincode.me/MGdkOwegfAa0PAlAgjER3zqF9v4ZZNh7", "info": {"w": 256, "h": 256, "size": 141056, "mimetype": "image/png", "thumbnail_url": "mxc://m.origincode.me/MGdkOwegfAa0PAlAgjER3zqF9v4ZZNh7", "thumbnail_info": {"w": 256, "h": 256, "size": 141056, "mimetype": "image/png"}}, "msgtype": "m.sticker", "id": "tg-114159788346048752", "net.maunium.telegram.sticker": {"pack": {"id": "114159788346048513", "short_name": "linuxdistro"}, "id": "114159788346048752", "emoticons": ["🐭"]}}, {"body": "⚡", "url": "mxc://m.origincode.me/60kSJEjsiQ0IG3hzjTgqtk1lJov5iCCs", "info": {"w": 256, "h": 256, "size": 68912, "mimetype": "image/png", "thumbnail_url": "mxc://m.origincode.me/60kSJEjsiQ0IG3hzjTgqtk1lJov5iCCs", "thumbnail_info": {"w": 256, "h": 256, "size": 68912, "mimetype": "image/png"}}, "msgtype": "m.sticker", "id": "tg-114159788346048754", "net.maunium.telegram.sticker": {"pack": {"id": "114159788346048513", "short_name": "linuxdistro"}, "id": "114159788346048754", "emoticons": ["⚡"]}}, {"body": "🎁", "url": "mxc://m.origincode.me/T3GfKH6jGuoFonmkWwnBBoVwAfr46Wut", "info": {"w": 256, "h": 256, "size": 15303, "mimetype": "image/png", "thumbnail_url": "mxc://m.origincode.me/T3GfKH6jGuoFonmkWwnBBoVwAfr46Wut", "thumbnail_info": {"w": 256, "h": 256, "size": 15303, "mimetype": "image/png"}}, "msgtype": "m.sticker", "id": "tg-114159788346048756", "net.maunium.telegram.sticker": {"pack": {"id": "114159788346048513", "short_name": "linuxdistro"}, "id": "114159788346048756", "emoticons": ["🎁"]}}, {"body": "🐟", "url": "mxc://m.origincode.me/vIA0ZPIyimRqP2e8yFMPpocDLpueZ5UM", "info": {"w": 256, "h": 256, "size": 42956, "mimetype": "image/png", "thumbnail_url": "mxc://m.origincode.me/vIA0ZPIyimRqP2e8yFMPpocDLpueZ5UM", "thumbnail_info": {"w": 256, "h": 256, "size": 42956, "mimetype": "image/png"}}, "msgtype": "m.sticker", "id": "tg-114159788346048758", "net.maunium.telegram.sticker": {"pack": {"id": "114159788346048513", "short_name": "linuxdistro"}, "id": "114159788346048758", "emoticons": ["🐟"]}}, {"body": "🎓", "url": "mxc://m.origincode.me/BPUVjVd62zeCMJGRVpdyfmvmNyyStUCu", "info": {"w": 256, "h": 256, "size": 54350, "mimetype": "image/png", "thumbnail_url": "mxc://m.origincode.me/BPUVjVd62zeCMJGRVpdyfmvmNyyStUCu", "thumbnail_info": {"w": 256, "h": 256, "size": 54350, "mimetype": "image/png"}}, "msgtype": "m.sticker", "id": "tg-114159788346048760", "net.maunium.telegram.sticker": {"pack": {"id": "114159788346048513", "short_name": "linuxdistro"}, "id": "114159788346048760", "emoticons": ["🎓"]}}, {"body": "🎹", "url": "mxc://m.origincode.me/xETSdWIVTbhcvfWP2gbbUflVfN09IDny", "info": {"w": 256, "h": 256, "size": 114077, "mimetype": "image/png", "thumbnail_url": "mxc://m.origincode.me/xETSdWIVTbhcvfWP2gbbUflVfN09IDny", "thumbnail_info": {"w": 256, "h": 256, "size": 114077, "mimetype": "image/png"}}, "msgtype": "m.sticker", "id": "tg-114159788346048825", "net.maunium.telegram.sticker": {"pack": {"id": "114159788346048513", "short_name": "linuxdistro"}, "id": "114159788346048825", "emoticons": ["🎹"]}}, {"body": "🎸", "url": "mxc://m.origincode.me/NfLiTEnZEFdIuq7Cth4ntp1hgpsBCGvq", "info": {"w": 256, "h": 256, "size": 150206, "mimetype": "image/png", "thumbnail_url": "mxc://m.origincode.me/NfLiTEnZEFdIuq7Cth4ntp1hgpsBCGvq", "thumbnail_info": {"w": 256, "h": 256, "size": 150206, "mimetype": "image/png"}}, "msgtype": "m.sticker", "id": "tg-114159788346048827", "net.maunium.telegram.sticker": {"pack": {"id": "114159788346048513", "short_name": "linuxdistro"}, "id": "114159788346048827", "emoticons": ["🎸"]}}, {"body": "🎤", "url": "mxc://m.origincode.me/3G4NOA1qXnz52n13dt6afykOgcINRBRk", "info": {"w": 256, "h": 256, "size": 188627, "mimetype": "image/png", "thumbnail_url": "mxc://m.origincode.me/3G4NOA1qXnz52n13dt6afykOgcINRBRk", "thumbnail_info": {"w": 256, "h": 256, "size": 188627, "mimetype": "image/png"}}, "msgtype": "m.sticker", "id": "tg-114159788346048829", "net.maunium.telegram.sticker": {"pack": {"id": "114159788346048513", "short_name": "linuxdistro"}, "id": "114159788346048829", "emoticons": ["🎤"]}}, {"body": "⚽", "url": "mxc://m.origincode.me/rI9mv6yGO50d6vJDrsRaB2rwhdQ5ewj9", "info": {"w": 256, "h": 256, "size": 349352, "mimetype": "image/png", "thumbnail_url": "mxc://m.origincode.me/rI9mv6yGO50d6vJDrsRaB2rwhdQ5ewj9", "thumbnail_info": {"w": 256, "h": 256, "size": 349352, "mimetype": "image/png"}}, "msgtype": "m.sticker", "id": "tg-114159788346048831", "net.maunium.telegram.sticker": {"pack": {"id": "114159788346048513", "short_name": "linuxdistro"}, "id": "114159788346048831", "emoticons": ["⚽"]}}, {"body": "👮", "url": "mxc://m.origincode.me/Coyn5SglCNcjiW8UOyEXwAxWruR4ASlB", "info": {"w": 256, "h": 256, "size": 176293, "mimetype": "image/png", "thumbnail_url": "mxc://m.origincode.me/Coyn5SglCNcjiW8UOyEXwAxWruR4ASlB", "thumbnail_info": {"w": 256, "h": 256, "size": 176293, "mimetype": "image/png"}}, "msgtype": "m.sticker", "id": "tg-114159788346048833", "net.maunium.telegram.sticker": {"pack": {"id": "114159788346048513", "short_name": "linuxdistro"}, "id": "114159788346048833", "emoticons": ["👮"]}}, {"body": "🚽", "url": "mxc://m.origincode.me/qBpneyKP7JeH3ICoLZ7GT5aGpZxcx9Oy", "info": {"w": 256, "h": 256, "size": 168769, "mimetype": "image/png", "thumbnail_url": "mxc://m.origincode.me/qBpneyKP7JeH3ICoLZ7GT5aGpZxcx9Oy", "thumbnail_info": {"w": 256, "h": 256, "size": 168769, "mimetype": "image/png"}}, "msgtype": "m.sticker", "id": "tg-114159788346048835", "net.maunium.telegram.sticker": {"pack": {"id": "114159788346048513", "short_name": "linuxdistro"}, "id": "114159788346048835", "emoticons": ["🚽"]}}, {"body": "🐧", "url": "mxc://m.origincode.me/miKRJDlXKSbwl84QaP1nGKX5Qc18uo3X", "info": {"w": 256, "h": 256, "size": 100184, "mimetype": "image/png", "thumbnail_url": "mxc://m.origincode.me/miKRJDlXKSbwl84QaP1nGKX5Qc18uo3X", "thumbnail_info": {"w": 256, "h": 256, "size": 100184, "mimetype": "image/png"}}, "msgtype": "m.sticker", "id": "tg-114159788346048898", "net.maunium.telegram.sticker": {"pack": {"id": "114159788346048513", "short_name": "linuxdistro"}, "id": "114159788346048898", "emoticons": ["🐧"]}}, {"body": "🐧", "url": "mxc://m.origincode.me/AqLqGqBR2av2IAhymo2CPinMj4acBb77", "info": {"w": 256, "h": 256, "size": 155667, "mimetype": "image/png", "thumbnail_url": "mxc://m.origincode.me/AqLqGqBR2av2IAhymo2CPinMj4acBb77", "thumbnail_info": {"w": 256, "h": 256, "size": 155667, "mimetype": "image/png"}}, "msgtype": "m.sticker", "id": "tg-114159788346048900", "net.maunium.telegram.sticker": {"pack": {"id": "114159788346048513", "short_name": "linuxdistro"}, "id": "114159788346048900", "emoticons": ["🐧"]}}, {"body": "🐧", "url": "mxc://m.origincode.me/9ckMG8Pe10Mxq0as4UsIbQrjZUbTISAz", "info": {"w": 256, "h": 256, "size": 96452, "mimetype": "image/png", "thumbnail_url": "mxc://m.origincode.me/9ckMG8Pe10Mxq0as4UsIbQrjZUbTISAz", "thumbnail_info": {"w": 256, "h": 256, "size": 96452, "mimetype": "image/png"}}, "msgtype": "m.sticker", "id": "tg-114159788346048909", "net.maunium.telegram.sticker": {"pack": {"id": "114159788346048513", "short_name": "linuxdistro"}, "id": "114159788346048909", "emoticons": ["🐧"]}}, {"body": "🐧", "url": "mxc://m.origincode.me/Q9cOIHCE2j3Sgb1OAvv9OkkNgQ2Oopvl", "info": {"w": 256, "h": 256, "size": 174685, "mimetype": "image/png", "thumbnail_url": "mxc://m.origincode.me/Q9cOIHCE2j3Sgb1OAvv9OkkNgQ2Oopvl", "thumbnail_info": {"w": 256, "h": 256, "size": 174685, "mimetype": "image/png"}}, "msgtype": "m.sticker", "id": "tg-114159788346048903", "net.maunium.telegram.sticker": {"pack": {"id": "114159788346048513", "short_name": "linuxdistro"}, "id": "114159788346048903", "emoticons": ["🐧"]}}, {"body": "🖨", "url": "mxc://m.origincode.me/puw13BnV0qYJKJwmHIKskkvApkSC5Sl2", "info": {"w": 256, "h": 256, "size": 117470, "mimetype": "image/png", "thumbnail_url": "mxc://m.origincode.me/puw13BnV0qYJKJwmHIKskkvApkSC5Sl2", "thumbnail_info": {"w": 256, "h": 256, "size": 117470, "mimetype": "image/png"}}, "msgtype": "m.sticker", "id": "tg-114159788346048905", "net.maunium.telegram.sticker": {"pack": {"id": "114159788346048513", "short_name": "linuxdistro"}, "id": "114159788346048905", "emoticons": ["🖨"]}}, {"body": "🖨", "url": "mxc://m.origincode.me/2dfWaiRT46glkMSe9TSaWYlVu9cXiTle", "info": {"w": 256, "h": 256, "size": 41458, "mimetype": "image/png", "thumbnail_url": "mxc://m.origincode.me/2dfWaiRT46glkMSe9TSaWYlVu9cXiTle", "thumbnail_info": {"w": 256, "h": 256, "size": 41458, "mimetype": "image/png"}}, "msgtype": "m.sticker", "id": "tg-114159788346048907", "net.maunium.telegram.sticker": {"pack": {"id": "114159788346048513", "short_name": "linuxdistro"}, "id": "114159788346048907", "emoticons": ["🖨"]}}, {"body": "👍", "url": "mxc://m.origincode.me/5qujkB19t8OZjWsecDVREYNN4Jkg0gRp", "info": {"w": 256, "h": 256, "size": 191890, "mimetype": "image/png", "thumbnail_url": "mxc://m.origincode.me/5qujkB19t8OZjWsecDVREYNN4Jkg0gRp", "thumbnail_info": {"w": 256, "h": 256, "size": 191890, "mimetype": "image/png"}}, "msgtype": "m.sticker", "id": "tg-114159788346049162", "net.maunium.telegram.sticker": {"pack": {"id": "114159788346048513", "short_name": "linuxdistro"}, "id": "114159788346049162", "emoticons": ["👍"]}}, {"body": "🍗", "url": "mxc://m.origincode.me/AIBSYEICKAjzEowRJLf2djTk07P04SXe", "info": {"w": 256, "h": 256, "size": 128074, "mimetype": "image/png", "thumbnail_url": "mxc://m.origincode.me/AIBSYEICKAjzEowRJLf2djTk07P04SXe", "thumbnail_info": {"w": 256, "h": 256, "size": 128074, "mimetype": "image/png"}}, "msgtype": "m.sticker", "id": "tg-114159788346049230", "net.maunium.telegram.sticker": {"pack": {"id": "114159788346048513", "short_name": "linuxdistro"}, "id": "114159788346049230", "emoticons": ["🖨", "🍗", "🍺", "🍔", "📊", "📈", "🗄"]}}, {"body": "😎", "url": "mxc://m.origincode.me/e6VDvNTAooBkYhcqJ7cTmcXnbRYc6wUz", "info": {"w": 256, "h": 256, "size": 95425, "mimetype": "image/png", "thumbnail_url": "mxc://m.origincode.me/e6VDvNTAooBkYhcqJ7cTmcXnbRYc6wUz", "thumbnail_info": {"w": 256, "h": 256, "size": 95425, "mimetype": "image/png"}}, "msgtype": "m.sticker", "id": "tg-114159788346049236", "net.maunium.telegram.sticker": {"pack": {"id": "114159788346048513", "short_name": "linuxdistro"}, "id": "114159788346049236", "emoticons": ["😎"]}}, {"body": "🎄", "url": "mxc://m.origincode.me/cXuFm4Cq87R2cp3GTVBYTDdAs10asvgc", "info": {"w": 256, "h": 256, "size": 197786, "mimetype": "image/png", "thumbnail_url": "mxc://m.origincode.me/cXuFm4Cq87R2cp3GTVBYTDdAs10asvgc", "thumbnail_info": {"w": 256, "h": 256, "size": 197786, "mimetype": "image/png"}}, "msgtype": "m.sticker", "id": "tg-6010544239530743821", "net.maunium.telegram.sticker": {"pack": {"id": "114159788346048513", "short_name": "linuxdistro"}, "id": "6010544239530743821", "emoticons": ["🎄", "🌲"]}}, {"body": "🤺", "url": "mxc://m.origincode.me/JgWzUuUnpz1eezZffS0Ntj2PRZbAUSfX", "info": {"w": 256, "h": 256, "size": 109377, "mimetype": "image/png", "thumbnail_url": "mxc://m.origincode.me/JgWzUuUnpz1eezZffS0Ntj2PRZbAUSfX", "thumbnail_info": {"w": 256, "h": 256, "size": 109377, "mimetype": "image/png"}}, "msgtype": "m.sticker", "id": "tg-6010612821568526086", "net.maunium.telegram.sticker": {"pack": {"id": "114159788346048513", "short_name": "linuxdistro"}, "id": "6010612821568526086", "emoticons": ["🤺", "⚔", "🗡"]}}]}